envalidate/__init__.py
envalidate/envalidate.py
envalidate/errors.py
envalidate-0.1.1.dist-info/METADATA
envalidate-0.1.1.dist-info/WHEEL
envalidate-0.1.1.dist-info/RECORD
