Metadata-Version: 2.1
Name: envalidate
Version: 0.1.1
Summary: Ensure that your environment variables are always valid, and totally type safe.
Home-page: https://github.com/mdlafrance/pygendocs
License: GPL-3.0-or-later
Author: mdlafrance
Author-email: maxlafrance97@gmail.com
Requires-Python: >=3.8,<4.0
Classifier: License :: OSI Approved :: GNU General Public License v3 or later (GPLv3+)
Classifier: Programming Language :: Python :: 3
Classifier: Programming Language :: Python :: 3.8
Classifier: Programming Language :: Python :: 3.9
Classifier: Programming Language :: Python :: 3.10
Classifier: Programming Language :: Python :: 3.11
Classifier: Programming Language :: Python :: 3.12
Requires-Dist: pydantic (>=2.9.1,<3.0.0)
Project-URL: Repository, https://github.com/mdlafrance/pygendocs
